dlt_sidestep/__init__.py
dlt_sidestep/main.py
dlt_sidestep-0.0.8.dist-info/LICENSE
dlt_sidestep-0.0.8.dist-info/METADATA
dlt_sidestep-0.0.8.dist-info/WHEEL
dlt_sidestep-0.0.8.dist-info/top_level.txt
dlt_sidestep-0.0.8.dist-info/RECORD
