Metadata-Version: 2.1
Name: dlt-sidestep
Version: 0.0.8
Summary: A library that helps you build dlt pipelines by side stepping the dlt library and making your code interactive
Author: Michael Gardner
Author-email: gardnmi@gmail.com
License: UNKNOWN
Keywords: python,databricks,dlt,delta live tables
Platform: UNKNOWN
Classifier: Development Status :: 5 - Production/Stable
Classifier: Intended Audience :: Developers
Classifier: Programming Language :: Python :: 3
Classifier: Operating System :: Unix
Classifier: Operating System :: MacOS :: MacOS X
Classifier: Operating System :: Microsoft :: Windows
License-File: LICENSE
